mongo_migrator/__init__.py
mongo_migrator/cli.py
mongo_migrator/config.py
mongo_migrator/db_utils.py
mongo_migrator/migration_history.py
mongo_migrator/migration_template.py
mongo_migrator-1.0.1.dist-info/LICENSE
mongo_migrator-1.0.1.dist-info/METADATA
mongo_migrator-1.0.1.dist-info/WHEEL
mongo_migrator-1.0.1.dist-info/entry_points.txt
mongo_migrator-1.0.1.dist-info/RECORD
