Metadata-Version: 2.3
Name: mongo-migrator
Version: 1.0.1
Summary: Simple MongoDB migrations tool.
License: MIT
Keywords: database,mongo,mongodb,pymongo,python,migration
Author: Álvaro Martín López
Author-email: almarlop.dev@gmail.com
Requires-Python: >=3.9,<=3.14
Classifier: Intended Audience :: Developers
Classifier: Operating System :: OS Independent
Classifier: License :: OSI Approved :: MIT License
Classifier: Programming Language :: Python :: 3
Classifier: Programming Language :: Python :: 3.9
Classifier: Programming Language :: Python :: 3.10
Classifier: Programming Language :: Python :: 3.11
Classifier: Programming Language :: Python :: 3.12
Classifier: Programming Language :: Python :: 3.13
Classifier: Programming Language :: Python :: 3.14
Classifier: Topic :: Database
Classifier: Topic :: Software Development :: Libraries :: Python Modules
Requires-Dist: pymongo (>=4.11.1,<5.0.0)
Project-URL: Repository, https://github.com/Alburrito/mongo-migrator
